protors-0.4.0.dist-info/METADATA
protors-0.4.0.dist-info/WHEEL
protors-0.4.0.dist-info/licenses/LICENSE
protors.pyi
protors/__init__.py
protors/__init__.pyi
protors/protors.cpython-313-x86_64-linux-gnu.so
protors/py.typed
protors-0.4.0.dist-info/RECORD
