Metadata-Version: 2.4
Name: protors
Version: 0.4.0
Classifier: Programming Language :: Rust
Classifier: Programming Language :: Python :: Implementation :: CPython
Classifier: Programming Language :: Python :: Implementation :: PyPy
License-File: LICENSE
Summary: Protobuff for Python
Author: pkozhem <pkozhem@gmail.com>
Author-email: pkozhem <pkozhem@gmail.com>
License: MIT OR Apache-2.0
Requires-Python: >=3.13
